{
  "Workflows": [
    {
      "Path": null,
      "SortBy": 0,
      "VariablesSectionElementsOrder": [],
      "ArgumentsSectionElementsOrder": null,
      "ConstantsSectionElementsOrder": [],
      "AddedNamespaces": null
    },
    {
      "Path": "Main.xaml",
      "SortBy": 0,
      "VariablesSectionElementsOrder": [
        "selectedRoom&Sequence_10",
        "selectedRooms&Sequence_2",
        "possibleRooms&Sequence_2",
        "originalPref&Sequence_2",
        "gender&Sequence_2",
        "dtUnallocated&Sequence_2",
        "roomNo&Sequence_2",
        "newRow&Sequence_2",
        "rowRoom&Sequence_2",
        "rowStudent&Sequence_2",
        "stuDT&Sequence_2",
        "roomsDT&Sequence_2",
        "dtAllocated&Sequence_2"
      ],
      "ArgumentsSectionElementsOrder": [],
      "ConstantsSectionElementsOrder": [],
      "AddedNamespaces": null
    }
  ]
}